emmet/builders/__init__.py
emmet/builders/py.typed
emmet/builders/settings.py
emmet/builders/utils.py
emmet/builders/abinit/__init__.py
emmet/builders/abinit/phonon.py
emmet/builders/abinit/sound_velocity.py
emmet/builders/feff/__init__.py
emmet/builders/feff/xas.py
emmet/builders/materials/__init__.py
emmet/builders/materials/absorption_spectrum.py
emmet/builders/materials/alloys.py
emmet/builders/materials/basic_descriptors.py
emmet/builders/materials/bonds.py
emmet/builders/materials/chemenv.py
emmet/builders/materials/corrected_entries.py
emmet/builders/materials/dielectric.py
emmet/builders/materials/elasticity.py
emmet/builders/materials/electrodes.py
emmet/builders/materials/electronic_structure.py
emmet/builders/materials/magnetism.py
emmet/builders/materials/optimade.py
emmet/builders/materials/oxidation_states.py
emmet/builders/materials/piezoelectric.py
emmet/builders/materials/provenance.py
emmet/builders/materials/robocrys.py
emmet/builders/materials/similarity.py
emmet/builders/materials/substrates.py
emmet/builders/materials/summary.py
emmet/builders/materials/thermo.py
emmet/builders/matscholar/missing_compositions.py
emmet/builders/mobility/__init__.py
emmet/builders/mobility/migration_graph.py
emmet/builders/vasp/__init__.py
emmet/builders/vasp/materials.py
emmet/builders/vasp/mp_potcar_stats.json.gz
emmet/builders/vasp/task_validator.py
emmet_builders-0.86.3.dist-info/METADATA
emmet_builders-0.86.3.dist-info/WHEEL
emmet_builders-0.86.3.dist-info/top_level.txt
emmet_builders-0.86.3.dist-info/RECORD
