Metadata-Version: 2.4
Name: emmet-builders
Version: 0.86.3
Summary: Builders for the Emmet Library
Author-email: The Materials Project <feedback@materialsproject.org>
License: Modified BSD
Project-URL: Homepage, https://github.com/materialsproject/emmet/tree/main/emmet-builders/
Project-URL: Documentation, https://materialsproject.github.io/emmet/
Requires-Python: >=3.11
Requires-Dist: emmet-core[all]>=0.85
Requires-Dist: maggma>=0.57.6
Requires-Dist: matminer>=0.10.0
Requires-Dist: pymatgen-io-validation>=0.1.1
Provides-Extra: test
Requires-Dist: pre-commit; extra == "test"
Requires-Dist: pytest; extra == "test"
Requires-Dist: pytest-cov; extra == "test"
Requires-Dist: pytest-xdist; extra == "test"
Requires-Dist: pycodestyle; extra == "test"
Requires-Dist: pydocstyle; extra == "test"
Requires-Dist: flake8; extra == "test"
Requires-Dist: mypy; extra == "test"
Requires-Dist: mypy-extensions; extra == "test"
Requires-Dist: types-setuptools; extra == "test"
Requires-Dist: types-requests; extra == "test"
Requires-Dist: wincertstore; extra == "test"
Provides-Extra: docs
Requires-Dist: mkdocs; extra == "docs"
Requires-Dist: mkdocs-material<8.3; extra == "docs"
Requires-Dist: mkdocs-material-extensions; extra == "docs"
Requires-Dist: mkdocs-minify-plugin; extra == "docs"
Requires-Dist: mkdocstrings; extra == "docs"
Requires-Dist: mkdocs-awesome-pages-plugin; extra == "docs"
Requires-Dist: mkdocs-markdownextradata-plugin; extra == "docs"
Requires-Dist: mkdocstrings[python]; extra == "docs"
Requires-Dist: livereload; extra == "docs"
Requires-Dist: jinja2; extra == "docs"
